LICENSE.txt
MANIFEST.in
README.rst
setup.py
version.txt
xtarfile/__init__.py
xtarfile/lz4.py
xtarfile/xtarfile.py
xtarfile/zstd.py
xtarfile.egg-info/PKG-INFO
xtarfile.egg-info/SOURCES.txt
xtarfile.egg-info/dependency_links.txt
xtarfile.egg-info/requires.txt
xtarfile.egg-info/top_level.txt