Metadata-Version: 2.1
Name: xtarfile
Version: 0.2.1
Summary: Wrapper around tarfile with support for more compression formats.
Home-page: https://github.com/ascoderu/xtarfile
Download-URL: https://pypi.python.org/pypi/xtarfile
Author: Clemens Wolff
Author-email: clemens.wolff+pypi@gmail.com
License: Apache Software License
Classifier: License :: OSI Approved :: Apache Software License
Classifier: Programming Language :: Python :: 3.4
Classifier: Programming Language :: Python :: 3.5
Classifier: Programming Language :: Python :: 3.6
Classifier: Topic :: Utilities
Requires-Python: >=3.4
Provides-Extra: lz4
Provides-Extra: zstd
License-File: LICENSE.txt
